analysis_tools/average_relatedness_by_year.py
analysis_tools/corpus_stats.py
analysis_tools/cosine_similarity_time_series.py
analysis_tools/semantic_drift.py
analysis_tools/weat_time_series.py
common/w2v_model.py
hist_w2v-0.1.6.dist-info/licenses/LICENSE
ngram_tools/__init__.py
ngram_tools/consolidate_ngrams.py
ngram_tools/convert_to_jsonl.py
ngram_tools/download_ngrams.py
ngram_tools/filter_ngrams.py
ngram_tools/index_and_create_vocab.py
ngram_tools/lemmatize_ngrams.py
ngram_tools/lowercase_ngrams.py
ngram_tools/make_yearly_files.py
ngram_tools/sort_ngrams.py
ngram_tools/helpers/__init__.py
ngram_tools/helpers/file_handler.py
ngram_tools/helpers/print_jsonl_lines.py
ngram_tools/helpers/save_stripped_ngrams.py
ngram_tools/helpers/verify_sort.py
training_tools/__init__.py
training_tools/evaluate_models.py
training_tools/normalize_and_align_models.py
training_tools/train_models.py
training_tools/helpers/plotting.py
hist_w2v-0.1.6.dist-info/METADATA
hist_w2v-0.1.6.dist-info/WHEEL
hist_w2v-0.1.6.dist-info/top_level.txt
hist_w2v-0.1.6.dist-info/RECORD
