Metadata-Version: 2.4
Name: hist_w2v
Version: 0.1.6
Summary: Tools for downloading, processing, and training word2vec models on Google Ngrams
Author-email: "Eric D. Knowles" <edk202@nyu.edu>
License: MIT
Project-URL: Homepage, https://github.com/eric-d-knowles/hist_w2v
Keywords: nlp,word2vec,ngrams,history
Classifier: Development Status :: 2 - Pre-Alpha
Classifier: Intended Audience :: Developers
Classifier: Programming Language :: Python :: 3
Classifier: Operating System :: OS Independent
Requires-Python: >=3.7
License-File: LICENSE
Requires-Dist: requests<3.0,>=2.2
Requires-Dist: tqdm<5.0,>=4.64
Requires-Dist: orjson<4.0,>=3.6
Requires-Dist: nltk<4.0,>=3.7
Requires-Dist: gensim<5.0,>=4.3.0
Requires-Dist: pandas<2.0,>=1.3.0
Requires-Dist: matplotlib<4.0,>=3.4
Requires-Dist: seaborn<1.0,>=0.11
Requires-Dist: ipympl<1.0,>=0.9.0
Requires-Dist: lz4<5.0,>=4.3.3
Dynamic: license-file
